[
    {
        "id": 54954993,
        "kind": 16,
        "quantity": 3773,
        "quality": 0,
        "price": 7.4,
        "seller": {
            "id": 1458707,
            "company": "Konag Asset",
            "realmId": 0,
            "logo": "https://d1fxy698ilbz6u.cloudfront.net/logo/a5d5e0b1531949dc898dd1c51c76e9d98096f147.png",
            "certificates": 1,
            "contest_wins": 0,
            "npc": false,
            "courseId": null,
            "ip": "812ed4"
        },
        "posted": "2023-03-17T11:27:40.734329+00:00",
        "fees": 0
    },
    {
        "id": 54957728,
        "kind": 16,
        "quantity": 2700,
        "quality": 0,
        "price": 7.4,
        "seller": {
            "id": 2852218,
            "company": "Golden Sky",
            "realmId": 0,
            "logo": "",
            "certificates": 0,
            "contest_wins": 0,
            "npc": false,
            "courseId": null,
            "ip": "2ebfdd"
        },
        "posted": "2023-03-17T12:21:39.136995+00:00",
        "fees": 600
    },
    {
        "id": 54957543,
        "kind": 16,
        "quantity": 6395,
        "quality": 2,
        "price": 7.5,
        "seller": {
            "id": 229713,
            "company": "Widgetron",
            "realmId": 0,
            "logo": "https://d1fxy698ilbz6u.cloudfront.net/logo/b2d87800ec34398bfc4156dd73c82e1c3c68be24.png",
            "certificates": 3,
            "contest_wins": 0,
            "npc": false,
            "courseId": null,
            "ip": "627513"
        },
        "posted": "2023-03-17T12:18:17.276312+00:00",
        "fees": 0
    },
    {
        "id": 54950929,
        "kind": 16,
        "quantity": 208567,
        "quality": 1,
        "price": 7.5,
        "seller": {
            "id": 2078656,
            "company": "Groupe lucky",
            "realmId": 0,
            "logo": "https://d1fxy698ilbz6u.cloudfront.net/logo/329b36240cfa6726a08eabd5e8380759c3bfcf99.png",
            "certificates": 1,
            "contest_wins": 0,
            "npc": false,
            "courseId": null,
            "ip": "589bd9"
        },
        "posted": "2023-03-17T10:01:11.270975+00:00",
        "fees": 0
    },
    {
        "id": 54955135,
        "kind": 16,
        "quantity": 612,
        "quality": 1,
        "price": 7.5,
        "seller": {
            "id": 2798332,
            "company": "Nord Holdig",
            "realmId": 0,
            "logo": "https://d1fxy698ilbz6u.cloudfront.net/logo/1a1b8078e58a171bb401d065b787dfd89059f3fb.png",
            "certificates": 0,
            "contest_wins": 0,
            "npc": false,
            "courseId": null,
            "ip": "f1e053"
        },
        "posted": "2023-03-17T11:30:51.574810+00:00",
        "fees": 138
    },
    {
        "id": 54958031,
        "kind": 16,
        "quantity": 1362,
        "quality": 1,
        "price": 7.5,
        "seller": {
            "id": 2727668,
            "company": "BORDER COMPAGNIE",
            "realmId": 0,
            "logo": "",
            "certificates": 0,
            "contest_wins": 0,
            "npc": false,
            "courseId": null,
            "ip": "19825a"
        },
        "posted": "2023-03-17T12:27:03.990571+00:00",
        "fees": 307
    },
    {
        "id": 54950204,
        "kind": 16,
        "quantity": 261,
        "quality": 0,
        "price": 7.5,
        "seller": {
            "id": 2786542,
            "company": "Jiff Inc",
            "realmId": 0,
            "logo": "",
            "certificates": 0,
            "contest_wins": 0,
            "npc": false,
            "courseId": null,
            "ip": "368492"
        },
        "posted": "2023-03-17T09:44:56.141938+00:00",
        "fees": 0
    },
    {
        "id": 54950815,
        "kind": 16,
        "quantity": 5580,
        "quality": 0,
        "price": 7.5,
        "seller": {
            "id": 2555564,
            "company": "Furkan Pazarlama",
            "realmId": 0,
            "logo": "",
            "certificates": 0,
            "contest_wins": 0,
            "npc": false,
            "courseId": null,
            "ip": "51bea5"
        },
        "posted": "2023-03-17T09:58:14.873474+00:00",
        "fees": 1256
    },
    {
        "id": 54953141,
        "kind": 16,
        "quantity": 17416,
        "quality": 0,
        "price": 7.5,
        "seller": {
            "id": 2701745,
            "company": "Cargo TSL",
            "realmId": 0,
            "logo": "",
            "certificates": 0,
            "contest_wins": 0,
            "npc": false,
            "courseId": null,
            "ip": "3249eb"
        },
        "posted": "2023-03-17T10:51:20.870072+00:00",
        "fees": 3919
    },
    {
        "id": 54953639,
        "kind": 16,
        "quantity": 62,
        "quality": 0,
        "price": 7.5,
        "seller": {
            "id": 435454,
            "company": "Kings Pawn Industries",
            "realmId": 0,
            "logo": "",
            "certificates": 2,
            "contest_wins": 0,
            "npc": false,
            "courseId": null,
            "ip": "28a603"
        },
        "posted": "2023-03-17T11:00:41.307344+00:00",
        "fees": 14
    },
    {
        "id": 54957971,
        "kind": 16,
        "quantity": 1213,
        "quality": 1,
        "price": 7.6,
        "seller": {
            "id": 2291844,
            "company": "SaintGraal",
            "realmId": 0,
            "logo": "",
            "certificates": 0,
            "contest_wins": 0,
            "npc": false,
            "courseId": null,
            "ip": "e571a0"
        },
        "posted": "2023-03-17T12:26:03.267712+00:00",
        "fees": 277
    },
    {
        "id": 54936871,
        "kind": 16,
        "quantity": 102005,
        "quality": 0,
        "price": 7.6,
        "seller": {
            "id": 2355959,
            "company": "Dark Gold Legacy",
            "realmId": 0,
            "logo": "https://d1fxy698ilbz6u.cloudfront.net/logo/6b2ba8b5768168c1d74b4bed9558944df3195a09.png",
            "certificates": 0,
            "contest_wins": 0,
            "npc": false,
            "courseId": null,
            "ip": "63c50b"
        },
        "posted": "2023-03-17T04:29:37.402121+00:00",
        "fees": 0
    },
    {
        "id": 54937002,
        "kind": 16,
        "quantity": 108,
        "quality": 0,
        "price": 7.6,
        "seller": {
            "id": 2921766,
            "company": "Ehtesham Emirates",
            "realmId": 0,
            "logo": "https://d1fxy698ilbz6u.cloudfront.net/logo/7bbe9808b62b8116ffb573fc2dd7576931f8540c.png",
            "certificates": 0,
            "contest_wins": 0,
            "npc": false,
            "courseId": null,
            "ip": "c848cc"
        },
        "posted": "2023-03-17T04:33:20.621612+00:00",
        "fees": 25
    },
    {
        "id": 54943621,
        "kind": 16,
        "quantity": 100,
        "quality": 0,
        "price": 7.6,
        "seller": {
            "id": 2879435,
            "company": "Rockwood Industrial",
            "realmId": 0,
            "logo": "https://d1fxy698ilbz6u.cloudfront.net/logo/72c14f7e98367b2d952a3f4f4e731f62f7e9b8d0.png",
            "certificates": 0,
            "contest_wins": 0,
            "npc": false,
            "courseId": null,
            "ip": "6ea007"
        },
        "posted": "2023-03-17T07:06:47.720026+00:00",
        "fees": 23
    },
    {
        "id": 54948836,
        "kind": 16,
        "quantity": 2529,
        "quality": 0,
        "price": 7.6,
        "seller": {
            "id": 2897373,
            "company": "Galaxy Trading Corp.",
            "realmId": 0,
            "logo": "https://d1fxy698ilbz6u.cloudfront.net/logo/c1b90bfdcbb4f72a74f60ffb7b3e6bc04a105ad3.png",
            "certificates": 0,
            "contest_wins": 0,
            "npc": false,
            "courseId": null,
            "ip": "ce0dfc"
        },
        "posted": "2023-03-17T09:12:12.621212+00:00",
        "fees": 577
    },
    {
        "id": 54949198,
        "kind": 16,
        "quantity": 440,
        "quality": 0,
        "price": 7.6,
        "seller": {
            "id": 2311857,
            "company": "AGRAWAL GROUP OF INDUSTRIES",
            "realmId": 0,
            "logo": "https://d1fxy698ilbz6u.cloudfront.net/logo/31b2c754e028c6ea8e928a2e07fa7872da7f1c61.png",
            "certificates": 0,
            "contest_wins": 0,
            "npc": false,
            "courseId": null,
            "ip": "f1d549"
        },
        "posted": "2023-03-17T09:20:56.056647+00:00",
        "fees": 101
    },
    {
        "id": 54949729,
        "kind": 16,
        "quantity": 16010,
        "quality": 0,
        "price": 7.6,
        "seller": {
            "id": 2762255,
            "company": "RJ Business Park LTD.",
            "realmId": 0,
            "logo": "https://d1fxy698ilbz6u.cloudfront.net/logo/adb216ae8d4a78d8e1111b5f19d0a68058c18e5a.png",
            "certificates": 0,
            "contest_wins": 0,
            "npc": false,
            "courseId": null,
            "ip": "240ed2"
        },
        "posted": "2023-03-17T09:33:36.291980+00:00",
        "fees": 3651
    },
    {
        "id": 54953632,
        "kind": 16,
        "quantity": 63,
        "quality": 0,
        "price": 7.6,
        "seller": {
            "id": 435454,
            "company": "Kings Pawn Industries",
            "realmId": 0,
            "logo": "",
            "certificates": 2,
            "contest_wins": 0,
            "npc": false,
            "courseId": null,
            "ip": "28a603"
        },
        "posted": "2023-03-17T11:00:34.545185+00:00",
        "fees": 15
    },
    {
        "id": 54949077,
        "kind": 16,
        "quantity": 7432,
        "quality": 0,
        "price": 7.6,
        "seller": {
            "id": 2136557,
            "company": "BLP LLP",
            "realmId": 0,
            "logo": "https://d1fxy698ilbz6u.cloudfront.net/logo/f16c3ab85a9047d93e1ad0597c17c43d9393b1a0.png",
            "certificates": 0,
            "contest_wins": 0,
            "npc": false,
            "courseId": null,
            "ip": "e591c8"
        },
        "posted": "2023-03-17T12:19:27.746826+00:00",
        "fees": 1696
    },
    {
        "id": 54956006,
        "kind": 16,
        "quantity": 11061,
        "quality": 3,
        "price": 7.7,
        "seller": {
            "id": 1197167,
            "company": "Trezton",
            "realmId": 0,
            "logo": "https://d1fxy698ilbz6u.cloudfront.net/logo/6bfa6d33f6c060db52761922a720a999e60236de.png",
            "certificates": 1,
            "contest_wins": 0,
            "npc": false,
            "courseId": null,
            "ip": "977dc1"
        },
        "posted": "2023-03-17T11:48:13.779330+00:00",
        "fees": 0
    },
    {
        "id": 54958038,
        "kind": 16,
        "quantity": 21922,
        "quality": 2,
        "price": 7.7,
        "seller": {
            "id": 2727668,
            "company": "BORDER COMPAGNIE",
            "realmId": 0,
            "logo": "",
            "certificates": 0,
            "contest_wins": 0,
            "npc": false,
            "courseId": null,
            "ip": "19825a"
        },
        "posted": "2023-03-17T12:27:11.380916+00:00",
        "fees": 5064
    },
    {
        "id": 54948303,
        "kind": 16,
        "quantity": 2856,
        "quality": 1,
        "price": 7.7,
        "seller": {
            "id": 2105629,
            "company": "FBG Partner",
            "realmId": 0,
            "logo": "",
            "certificates": 0,
            "contest_wins": 0,
            "npc": false,
            "courseId": null,
            "ip": "67fb7d"
        },
        "posted": "2023-03-17T09:00:06.216918+00:00",
        "fees": 660
    },
    {
        "id": 54318947,
        "kind": 16,
        "quantity": 99235,
        "quality": 0,
        "price": 7.7,
        "seller": {
            "id": 2757043,
            "company": "Moutata6",
            "realmId": 0,
            "logo": "",
            "certificates": 0,
            "contest_wins": 0,
            "npc": false,
            "courseId": null,
            "ip": "c4a707"
        },
        "posted": "2023-03-12T02:59:10.676826+00:00",
        "fees": 0
    },
    {
        "id": 54835753,
        "kind": 16,
        "quantity": 472,
        "quality": 0,
        "price": 7.7,
        "seller": {
            "id": 1458707,
            "company": "Konag Asset",
            "realmId": 0,
            "logo": "https://d1fxy698ilbz6u.cloudfront.net/logo/a5d5e0b1531949dc898dd1c51c76e9d98096f147.png",
            "certificates": 1,
            "contest_wins": 0,
            "npc": false,
            "courseId": null,
            "ip": "812ed4"
        },
        "posted": "2023-03-15T15:31:30.753777+00:00",
        "fees": 110
    },
    {
        "id": 54904628,
        "kind": 16,
        "quantity": 18395,
        "quality": 0,
        "price": 7.7,
        "seller": {
            "id": 2048753,
            "company": "Cheaper Than A DUI",
            "realmId": 0,
            "logo": "",
            "certificates": 0,
            "contest_wins": 0,
            "npc": false,
            "courseId": null,
            "ip": "356bd9"
        },
        "posted": "2023-03-16T16:25:06.459568+00:00",
        "fees": 4250
    },
    {
        "id": 54905013,
        "kind": 16,
        "quantity": 9123,
        "quality": 0,
        "price": 7.7,
        "seller": {
            "id": 1451735,
            "company": "Cypis rus lcc",
            "realmId": 0,
            "logo": "",
            "certificates": 1,
            "contest_wins": 0,
            "npc": false,
            "courseId": null,
            "ip": "566ea0"
        },
        "posted": "2023-03-16T16:32:59.377968+00:00",
        "fees": 2108
    },
    {
        "id": 54905774,
        "kind": 16,
        "quantity": 7620,
        "quality": 0,
        "price": 7.7,
        "seller": {
            "id": 2707899,
            "company": "Solaris Incorporation",
            "realmId": 0,
            "logo": "https://d1fxy698ilbz6u.cloudfront.net/logo/c3977aa02b4e7f86b58adfa259cde7513fa11b5f.png",
            "certificates": 0,
            "contest_wins": 0,
            "npc": false,
            "courseId": null,
            "ip": "04a528"
        },
        "posted": "2023-03-16T16:47:54.128555+00:00",
        "fees": 1761
    },
    {
        "id": 54909377,
        "kind": 16,
        "quantity": 780,
        "quality": 0,
        "price": 7.7,
        "seller": {
            "id": 2897373,
            "company": "Galaxy Trading Corp.",
            "realmId": 0,
            "logo": "https://d1fxy698ilbz6u.cloudfront.net/logo/c1b90bfdcbb4f72a74f60ffb7b3e6bc04a105ad3.png",
            "certificates": 0,
            "contest_wins": 0,
            "npc": false,
            "courseId": null,
            "ip": "ce0dfc"
        },
        "posted": "2023-03-16T17:58:01.646376+00:00",
        "fees": 181
    },
    {
        "id": 54905984,
        "kind": 16,
        "quantity": 1981,
        "quality": 0,
        "price": 7.7,
        "seller": {
            "id": 2136557,
            "company": "BLP LLP",
            "realmId": 0,
            "logo": "https://d1fxy698ilbz6u.cloudfront.net/logo/f16c3ab85a9047d93e1ad0597c17c43d9393b1a0.png",
            "certificates": 0,
            "contest_wins": 0,
            "npc": false,
            "courseId": null,
            "ip": "6f38b1"
        },
        "posted": "2023-03-16T18:29:20.728912+00:00",
        "fees": 459
    },
    {
        "id": 54935663,
        "kind": 16,
        "quantity": 150,
        "quality": 0,
        "price": 7.7,
        "seller": {
            "id": 2921766,
            "company": "Ehtesham Emirates",
            "realmId": 0,
            "logo": "https://d1fxy698ilbz6u.cloudfront.net/logo/7bbe9808b62b8116ffb573fc2dd7576931f8540c.png",
            "certificates": 0,
            "contest_wins": 0,
            "npc": false,
            "courseId": null,
            "ip": "c848cc"
        },
        "posted": "2023-03-17T03:51:37.987388+00:00",
        "fees": 35
    },
    {
        "id": 54953628,
        "kind": 16,
        "quantity": 64,
        "quality": 0,
        "price": 7.7,
        "seller": {
            "id": 435454,
            "company": "Kings Pawn Industries",
            "realmId": 0,
            "logo": "",
            "certificates": 2,
            "contest_wins": 0,
            "npc": false,
            "courseId": null,
            "ip": "28a603"
        },
        "posted": "2023-03-17T11:00:30.007535+00:00",
        "fees": 15
    },
    {
        "id": 54946968,
        "kind": 16,
        "quantity": 16555,
        "quality": 3,
        "price": 7.8,
        "seller": {
            "id": 1436736,
            "company": "WO Imperial",
            "realmId": 0,
            "logo": "",
            "certificates": 1,
            "contest_wins": 0,
            "npc": false,
            "courseId": null,
            "ip": "a77ad5"
        },
        "posted": "2023-03-17T08:25:02.165590+00:00",
        "fees": 3874
    },
    {
        "id": 54946469,
        "kind": 16,
        "quantity": 11425,
        "quality": 3,
        "price": 7.8,
        "seller": {
            "id": 2042318,
            "company": "PaukyTrans",
            "realmId": 0,
            "logo": "https://d1fxy698ilbz6u.cloudfront.net/logo/f44bed20eac7e08a6ac89c996f2bb6bcd8d31658.png",
            "certificates": 0,
            "contest_wins": 0,
            "npc": false,
            "courseId": null,
            "ip": "cb99a4"
        },
        "posted": "2023-03-17T09:30:49.587690+00:00",
        "fees": 856
    },
    {
        "id": 54951746,
        "kind": 16,
        "quantity": 34400,
        "quality": 3,
        "price": 7.8,
        "seller": {
            "id": 2568683,
            "company": "1.2.4.8.16.32.64...Ilimited",
            "realmId": 0,
            "logo": "https://d1fxy698ilbz6u.cloudfront.net/logo/507c5969609ee939904d717887500c2fe19a996e.png",
            "certificates": 0,
            "contest_wins": 0,
            "npc": false,
            "courseId": null,
            "ip": "506d47"
        },
        "posted": "2023-03-17T10:19:51.731496+00:00",
        "fees": 8050
    },
    {
        "id": 54543402,
        "kind": 16,
        "quantity": 252409,
        "quality": 2,
        "price": 7.8,
        "seller": {
            "id": 1475498,
            "company": "Moj Kram",
            "realmId": 0,
            "logo": "",
            "certificates": 1,
            "contest_wins": 0,
            "npc": false,
            "courseId": null,
            "ip": "d79eb2"
        },
        "posted": "2023-03-11T07:46:59.194977+00:00",
        "fees": 0
    },
    {
        "id": 54639302,
        "kind": 16,
        "quantity": 2449,
        "quality": 2,
        "price": 7.8,
        "seller": {
            "id": 1642539,
            "company": "Yucel2087",
            "realmId": 0,
            "logo": "https://d1fxy698ilbz6u.cloudfront.net/logo/bef4d7f6ee008b6123793dcc4cf775e547f3e890.png",
            "certificates": 1,
            "contest_wins": 0,
            "npc": false,
            "courseId": null,
            "ip": "68e0c1"
        },
        "posted": "2023-03-12T17:31:31.523883+00:00",
        "fees": 574
    },
    {
        "id": 54806028,
        "kind": 16,
        "quantity": 6000,
        "quality": 2,
        "price": 7.8,
        "seller": {
            "id": 1270568,
            "company": "iThink",
            "realmId": 0,
            "logo": "https://d1fxy698ilbz6u.cloudfront.net/logo/412959ff54c70ecb1d4691452ede6bd7b2e84234.png",
            "certificates": 1,
            "contest_wins": 0,
            "npc": false,
            "courseId": null,
            "ip": "97cf45"
        },
        "posted": "2023-03-15T04:35:03.331807+00:00",
        "fees": 1404
    },
    {
        "id": 54913109,
        "kind": 16,
        "quantity": 7333,
        "quality": 2,
        "price": 7.8,
        "seller": {
            "id": 1618099,
            "company": "Brazen trios",
            "realmId": 0,
            "logo": "https://d1fxy698ilbz6u.cloudfront.net/logo/2e9bff00ff3adebde4279606c26e7e900b982807.png",
            "certificates": 1,
            "contest_wins": 0,
            "npc": false,
            "courseId": null,
            "ip": "a2517e"
        },
        "posted": "2023-03-16T19:09:05.513341+00:00",
        "fees": 1716
    },
    {
        "id": 54570282,
        "kind": 16,
        "quantity": 115000,
        "quality": 2,
        "price": 7.8,
        "seller": {
            "id": 2724416,
            "company": "EMD Hardware",
            "realmId": 0,
            "logo": "https://d1fxy698ilbz6u.cloudfront.net/logo/b63cfe56dbc9151e9611fd4b0e8f16abd02e33da.png",
            "certificates": 0,
            "contest_wins": 0,
            "npc": false,
            "courseId": null,
            "ip": "966981"
        },
        "posted": "2023-03-16T22:56:08.627962+00:00",
        "fees": 26910
    },
    {
        "id": 54538693,
        "kind": 16,
        "quantity": 18652,
        "quality": 2,
        "price": 7.8,
        "seller": {
            "id": 1148468,
            "company": "Samy International Italia",
            "realmId": 0,
            "logo": "",
            "certificates": 1,
            "contest_wins": 0,
            "npc": false,
            "courseId": null,
            "ip": "7d3f9a"
        },
        "posted": "2023-03-17T06:02:47.432889+00:00",
        "fees": 3294
    },
    {
        "id": 54639308,
        "kind": 16,
        "quantity": 11824,
        "quality": 1,
        "price": 7.8,
        "seller": {
            "id": 1642539,
            "company": "Yucel2087",
            "realmId": 0,
            "logo": "https://d1fxy698ilbz6u.cloudfront.net/logo/bef4d7f6ee008b6123793dcc4cf775e547f3e890.png",
            "certificates": 1,
            "contest_wins": 0,
            "npc": false,
            "courseId": null,
            "ip": "68e0c1"
        },
        "posted": "2023-03-12T17:31:36.013255+00:00",
        "fees": 2767
    },
    {
        "id": 54937135,
        "kind": 16,
        "quantity": 112644,
        "quality": 1,
        "price": 7.8,
        "seller": {
            "id": 476082,
            "company": "Ivalice Corp",
            "realmId": 0,
            "logo": "https://d1fxy698ilbz6u.cloudfront.net/logo/486ae9f2d6896940e0e95d3b3b6d7c146c5e4e61.png",
            "certificates": 2,
            "contest_wins": 0,
            "npc": false,
            "courseId": null,
            "ip": "852f76"
        },
        "posted": "2023-03-17T04:37:21.380610+00:00",
        "fees": 26359
    },
    {
        "id": 54559899,
        "kind": 16,
        "quantity": 50800,
        "quality": 0,
        "price": 7.8,
        "seller": {
            "id": 1963141,
            "company": "Cangoo",
            "realmId": 0,
            "logo": "",
            "certificates": 0,
            "contest_wins": 0,
            "npc": false,
            "courseId": null,
            "ip": "f61902"
        },
        "posted": "2023-03-11T13:24:15.745670+00:00",
        "fees": 11888
    },
    {
        "id": 54951122,
        "kind": 16,
        "quantity": 638,
        "quality": 0,
        "price": 7.8,
        "seller": {
            "id": 3006699,
            "company": "MKrunal Trader",
            "realmId": 0,
            "logo": "https://d1fxy698ilbz6u.cloudfront.net/logo/dab997efd18a6a5395481ab27823f714bfc6e537.png",
            "certificates": 0,
            "contest_wins": 0,
            "npc": false,
            "courseId": null,
            "ip": "574d1f"
        },
        "posted": "2023-03-17T10:05:51.560988+00:00",
        "fees": 150
    },
    {
        "id": 54953625,
        "kind": 16,
        "quantity": 64,
        "quality": 0,
        "price": 7.8,
        "seller": {
            "id": 435454,
            "company": "Kings Pawn Industries",
            "realmId": 0,
            "logo": "",
            "certificates": 2,
            "contest_wins": 0,
            "npc": false,
            "courseId": null,
            "ip": "28a603"
        },
        "posted": "2023-03-17T11:00:25.374820+00:00",
        "fees": 15
    },
    {
        "id": 54341381,
        "kind": 16,
        "quantity": 174734,
        "quality": 5,
        "price": 7.9,
        "seller": {
            "id": 2318190,
            "company": "DOSUNG",
            "realmId": 0,
            "logo": "",
            "certificates": 0,
            "contest_wins": 0,
            "npc": false,
            "courseId": null,
            "ip": "a41aa9"
        },
        "posted": "2023-03-10T15:52:17.383630+00:00",
        "fees": 0
    },
    {
        "id": 54534436,
        "kind": 16,
        "quantity": 393604,
        "quality": 5,
        "price": 7.9,
        "seller": {
            "id": 1666095,
            "company": "King of Silicon",
            "realmId": 0,
            "logo": "https://d1fxy698ilbz6u.cloudfront.net/logo/b1b30d883fc7079dafb30c786057d062a504529d.png",
            "certificates": 10,
            "contest_wins": 0,
            "npc": false,
            "courseId": null,
            "ip": "97624c"
        },
        "posted": "2023-03-11T12:29:33.644224+00:00",
        "fees": 93286
    },
    {
        "id": 54883155,
        "kind": 16,
        "quantity": 139552,
        "quality": 4,
        "price": 7.9,
        "seller": {
            "id": 2373824,
            "company": "Cometa Enterprise Inc",
            "realmId": 0,
            "logo": "",
            "certificates": 0,
            "contest_wins": 0,
            "npc": false,
            "courseId": null,
            "ip": "16475f"
        },
        "posted": "2023-03-16T09:04:23.269149+00:00",
        "fees": 33074
    },
    {
        "id": 54215105,
        "kind": 16,
        "quantity": 398000,
        "quality": 3,
        "price": 7.9,
        "seller": {
            "id": 1366803,
            "company": "ZPU OBOJNIAK",
            "realmId": 0,
            "logo": "",
            "certificates": 1,
            "contest_wins": 0,
            "npc": false,
            "courseId": null,
            "ip": "b1e501"
        },
        "posted": "2023-03-06T10:44:38.137238+00:00",
        "fees": 0
    },
    {
        "id": 54504875,
        "kind": 16,
        "quantity": 15000,
        "quality": 3,
        "price": 7.9,
        "seller": {
            "id": 2735460,
            "company": "Cyclebum Inc",
            "realmId": 0,
            "logo": "https://d1fxy698ilbz6u.cloudfront.net/logo/5d0502626c977f7752111f6e995031f3f8192bce.png",
            "certificates": 1,
            "contest_wins": 0,
            "npc": false,
            "courseId": null,
            "ip": "64d710"
        },
        "posted": "2023-03-10T17:07:09.766078+00:00",
        "fees": 3555
    },
    {
        "id": 54844108,
        "kind": 16,
        "quantity": 5000,
        "quality": 3,
        "price": 7.9,
        "seller": {
            "id": 491274,
            "company": "Jalahema",
            "realmId": 0,
            "logo": "https://d1fxy698ilbz6u.cloudfront.net/logo/5a137b960810f135014baad54631756e5aeb4402.png",
            "certificates": 2,
            "contest_wins": 0,
            "npc": false,
            "courseId": null,
            "ip": "fca455"
        },
        "posted": "2023-03-15T18:16:23.341801+00:00",
        "fees": 1185
    },
    {
        "id": 54867739,
        "kind": 16,
        "quantity": 10043,
        "quality": 3,
        "price": 7.9,
        "seller": {
            "id": 2553968,
            "company": "Brostt Co",
            "realmId": 0,
            "logo": "",
            "certificates": 0,
            "contest_wins": 0,
            "npc": false,
            "courseId": null,
            "ip": "4b0ad7"
        },
        "posted": "2023-03-16T02:35:33.504338+00:00",
        "fees": 2381
    },
    {
        "id": 54936067,
        "kind": 16,
        "quantity": 25000,
        "quality": 3,
        "price": 7.9,
        "seller": {
            "id": 1432818,
            "company": "LinRayMeg Group",
            "realmId": 0,
            "logo": "https://d1fxy698ilbz6u.cloudfront.net/logo/ae1d4d5b6b4de4b00827eb6122bd82f04baa8423.png",
            "certificates": 1,
            "contest_wins": 0,
            "npc": false,
            "courseId": null,
            "ip": "aaa86a"
        },
        "posted": "2023-03-17T04:04:36.043404+00:00",
        "fees": 5925
    },
    {
        "id": 54953620,
        "kind": 16,
        "quantity": 65,
        "quality": 0,
        "price": 7.9,
        "seller": {
            "id": 435454,
            "company": "Kings Pawn Industries",
            "realmId": 0,
            "logo": "",
            "certificates": 2,
            "contest_wins": 0,
            "npc": false,
            "courseId": null,
            "ip": "28a603"
        },
        "posted": "2023-03-17T11:00:20.270582+00:00",
        "fees": 16
    },
    {
        "id": 54663288,
        "kind": 16,
        "quantity": 100000,
        "quality": 7,
        "price": 8.0,
        "seller": {
            "id": 951597,
            "company": "DOA Motors Company",
            "realmId": 0,
            "logo": "https://d1fxy698ilbz6u.cloudfront.net/logo/9c773fef48172b1b1a2e487e2ae4c2ab09993cb8.png",
            "certificates": 7,
            "contest_wins": 0,
            "npc": false,
            "courseId": null,
            "ip": "2f3d09"
        },
        "posted": "2023-03-13T00:53:01.999406+00:00",
        "fees": 24000
    },
    {
        "id": 54161101,
        "kind": 16,
        "quantity": 400000,
        "quality": 5,
        "price": 8.0,
        "seller": {
            "id": 1666095,
            "company": "King of Silicon",
            "realmId": 0,
            "logo": "https://d1fxy698ilbz6u.cloudfront.net/logo/b1b30d883fc7079dafb30c786057d062a504529d.png",
            "certificates": 10,
            "contest_wins": 0,
            "npc": false,
            "courseId": null,
            "ip": "f2c38d"
        },
        "posted": "2023-03-05T06:30:25.043032+00:00",
        "fees": 0
    },
    {
        "id": 54511670,
        "kind": 16,
        "quantity": 350000,
        "quality": 3,
        "price": 8.0,
        "seller": {
            "id": 2262373,
            "company": "bla359",
            "realmId": 0,
            "logo": "https://d1fxy698ilbz6u.cloudfront.net/logo/2bcfeb635711edaf9fb43626f230100aa9824b1c.png",
            "certificates": 0,
            "contest_wins": 0,
            "npc": false,
            "courseId": null,
            "ip": "53661e"
        },
        "posted": "2023-03-10T19:15:45.371727+00:00",
        "fees": 84000
    },
    {
        "id": 54844119,
        "kind": 16,
        "quantity": 5000,
        "quality": 3,
        "price": 8.0,
        "seller": {
            "id": 491274,
            "company": "Jalahema",
            "realmId": 0,
            "logo": "https://d1fxy698ilbz6u.cloudfront.net/logo/5a137b960810f135014baad54631756e5aeb4402.png",
            "certificates": 2,
            "contest_wins": 0,
            "npc": false,
            "courseId": null,
            "ip": "fca455"
        },
        "posted": "2023-03-15T18:16:31.064512+00:00",
        "fees": 1200
    },
    {
        "id": 54946138,
        "kind": 16,
        "quantity": 15000,
        "quality": 3,
        "price": 8.0,
        "seller": {
            "id": 2735460,
            "company": "Cyclebum Inc",
            "realmId": 0,
            "logo": "https://d1fxy698ilbz6u.cloudfront.net/logo/5d0502626c977f7752111f6e995031f3f8192bce.png",
            "certificates": 1,
            "contest_wins": 0,
            "npc": false,
            "courseId": null,
            "ip": "f4b56e"
        },
        "posted": "2023-03-17T08:05:32.878543+00:00",
        "fees": 3600
    },
    {
        "id": 54510784,
        "kind": 16,
        "quantity": 40000,
        "quality": 2,
        "price": 8.0,
        "seller": {
            "id": 2375250,
            "company": "Gospo Kompany",
            "realmId": 0,
            "logo": "",
            "certificates": 0,
            "contest_wins": 0,
            "npc": false,
            "courseId": null,
            "ip": "e86982"
        },
        "posted": "2023-03-10T19:00:20.901247+00:00",
        "fees": 9600
    },
    {
        "id": 54550688,
        "kind": 16,
        "quantity": 13830,
        "quality": 2,
        "price": 8.0,
        "seller": {
            "id": 1886512,
            "company": "Perkys Ltd",
            "realmId": 0,
            "logo": "https://d1fxy698ilbz6u.cloudfront.net/logo/0f5e3f442c3e484fef0018cb361f540d6fbd428d.png",
            "certificates": 0,
            "contest_wins": 0,
            "npc": false,
            "courseId": null,
            "ip": "7d6f26"
        },
        "posted": "2023-03-11T10:22:14.364444+00:00",
        "fees": 3320
    },
    {
        "id": 54953612,
        "kind": 16,
        "quantity": 66,
        "quality": 0,
        "price": 8.0,
        "seller": {
            "id": 435454,
            "company": "Kings Pawn Industries",
            "realmId": 0,
            "logo": "",
            "certificates": 2,
            "contest_wins": 0,
            "npc": false,
            "courseId": null,
            "ip": "28a603"
        },
        "posted": "2023-03-17T11:00:14.426972+00:00",
        "fees": 16
    },
    {
        "id": 54479283,
        "kind": 16,
        "quantity": 9807,
        "quality": 7,
        "price": 8.1,
        "seller": {
            "id": 98583,
            "company": "Mountaineers",
            "realmId": 0,
            "logo": "https://d1fxy698ilbz6u.cloudfront.net/logo/37890a08dea18a8dd936216c448ce9188ce1b3bf.png",
            "certificates": 10,
            "contest_wins": 0,
            "npc": false,
            "courseId": null,
            "ip": "a58f0a"
        },
        "posted": "2023-03-10T08:21:54.877438+00:00",
        "fees": 2384
    },
    {
        "id": 54957621,
        "kind": 16,
        "quantity": 15000,
        "quality": 3,
        "price": 8.1,
        "seller": {
            "id": 2215118,
            "company": "Thaumatin",
            "realmId": 0,
            "logo": "https://d1fxy698ilbz6u.cloudfront.net/logo/e6149e159f43281a691553012146558581452495.png",
            "certificates": 0,
            "contest_wins": 0,
            "npc": false,
            "courseId": null,
            "ip": "e0793b"
        },
        "posted": "2023-03-17T12:19:38.778496+00:00",
        "fees": 3645
    },
    {
        "id": 54953607,
        "kind": 16,
        "quantity": 66,
        "quality": 0,
        "price": 8.1,
        "seller": {
            "id": 435454,
            "company": "Kings Pawn Industries",
            "realmId": 0,
            "logo": "",
            "certificates": 2,
            "contest_wins": 0,
            "npc": false,
            "courseId": null,
            "ip": "28a603"
        },
        "posted": "2023-03-17T11:00:10.334853+00:00",
        "fees": 17
    },
    {
        "id": 54763079,
        "kind": 16,
        "quantity": 128869,
        "quality": 7,
        "price": 8.2,
        "seller": {
            "id": 1491422,
            "company": "J.M.F. Company Ltda",
            "realmId": 0,
            "logo": "",
            "certificates": 1,
            "contest_wins": 0,
            "npc": false,
            "courseId": null,
            "ip": "265cc4"
        },
        "posted": "2023-03-14T13:19:55.041143+00:00",
        "fees": 31702
    },
    {
        "id": 54591578,
        "kind": 16,
        "quantity": 29223,
        "quality": 3,
        "price": 8.2,
        "seller": {
            "id": 2553968,
            "company": "Brostt Co",
            "realmId": 0,
            "logo": "",
            "certificates": 0,
            "contest_wins": 0,
            "npc": false,
            "courseId": null,
            "ip": "4b0ad7"
        },
        "posted": "2023-03-11T23:41:22.688261+00:00",
        "fees": 7189
    },
    {
        "id": 54953602,
        "kind": 16,
        "quantity": 67,
        "quality": 0,
        "price": 8.2,
        "seller": {
            "id": 435454,
            "company": "Kings Pawn Industries",
            "realmId": 0,
            "logo": "",
            "certificates": 2,
            "contest_wins": 0,
            "npc": false,
            "courseId": null,
            "ip": "28a603"
        },
        "posted": "2023-03-17T11:00:05.007104+00:00",
        "fees": 17
    },
    {
        "id": 54957608,
        "kind": 16,
        "quantity": 25000,
        "quality": 3,
        "price": 8.3,
        "seller": {
            "id": 2215118,
            "company": "Thaumatin",
            "realmId": 0,
            "logo": "https://d1fxy698ilbz6u.cloudfront.net/logo/e6149e159f43281a691553012146558581452495.png",
            "certificates": 0,
            "contest_wins": 0,
            "npc": false,
            "courseId": null,
            "ip": "e0793b"
        },
        "posted": "2023-03-17T12:19:23.222003+00:00",
        "fees": 6226
    },
    {
        "id": 54953597,
        "kind": 16,
        "quantity": 68,
        "quality": 0,
        "price": 8.3,
        "seller": {
            "id": 435454,
            "company": "Kings Pawn Industries",
            "realmId": 0,
            "logo": "",
            "certificates": 2,
            "contest_wins": 0,
            "npc": false,
            "courseId": null,
            "ip": "28a603"
        },
        "posted": "2023-03-17T10:59:59.782572+00:00",
        "fees": 17
    },
    {
        "id": 54644187,
        "kind": 16,
        "quantity": 15000,
        "quality": 3,
        "price": 8.4,
        "seller": {
            "id": 2215118,
            "company": "Thaumatin",
            "realmId": 0,
            "logo": "https://d1fxy698ilbz6u.cloudfront.net/logo/e6149e159f43281a691553012146558581452495.png",
            "certificates": 0,
            "contest_wins": 0,
            "npc": false,
            "courseId": null,
            "ip": "c2d7d8"
        },
        "posted": "2023-03-12T18:57:55.545532+00:00",
        "fees": 3780
    },
    {
        "id": 54953591,
        "kind": 16,
        "quantity": 68,
        "quality": 0,
        "price": 8.4,
        "seller": {
            "id": 435454,
            "company": "Kings Pawn Industries",
            "realmId": 0,
            "logo": "",
            "certificates": 2,
            "contest_wins": 0,
            "npc": false,
            "courseId": null,
            "ip": "28a603"
        },
        "posted": "2023-03-17T10:59:55.034273+00:00",
        "fees": 18
    },
    {
        "id": 54550972,
        "kind": 16,
        "quantity": 5588,
        "quality": 1,
        "price": 8.5,
        "seller": {
            "id": 894140,
            "company": "AWA MARKETPLACE",
            "realmId": 0,
            "logo": "https://d1fxy698ilbz6u.cloudfront.net/logo/f737f48f080618c99e66d8b8c14a649fb7c1bcea.png",
            "certificates": 2,
            "contest_wins": 0,
            "npc": false,
            "courseId": null,
            "ip": "deb9a0"
        },
        "posted": "2023-03-11T10:27:48.941558+00:00",
        "fees": 1425
    },
    {
        "id": 54779957,
        "kind": 16,
        "quantity": 6043,
        "quality": 1,
        "price": 8.5,
        "seller": {
            "id": 2060232,
            "company": "Terrebly Mining Company",
            "realmId": 0,
            "logo": "https://d1fxy698ilbz6u.cloudfront.net/logo/13a1ec1c4a58ac34965eabc9133bea13c2665606.png",
            "certificates": 1,
            "contest_wins": 0,
            "npc": false,
            "courseId": null,
            "ip": "3f9fa9"
        },
        "posted": "2023-03-14T18:52:21.858525+00:00",
        "fees": 1541
    },
    {
        "id": 54953563,
        "kind": 16,
        "quantity": 69,
        "quality": 0,
        "price": 8.5,
        "seller": {
            "id": 435454,
            "company": "Kings Pawn Industries",
            "realmId": 0,
            "logo": "",
            "certificates": 2,
            "contest_wins": 0,
            "npc": false,
            "courseId": null,
            "ip": "28a603"
        },
        "posted": "2023-03-17T10:59:13.102950+00:00",
        "fees": 18
    },
    {
        "id": 54692710,
        "kind": 16,
        "quantity": 30000,
        "quality": 3,
        "price": 8.6,
        "seller": {
            "id": 2215118,
            "company": "Thaumatin",
            "realmId": 0,
            "logo": "https://d1fxy698ilbz6u.cloudfront.net/logo/e6149e159f43281a691553012146558581452495.png",
            "certificates": 0,
            "contest_wins": 0,
            "npc": false,
            "courseId": null,
            "ip": "5dfb47"
        },
        "posted": "2023-03-13T12:31:41.442430+00:00",
        "fees": 7740
    },
    {
        "id": 54550983,
        "kind": 16,
        "quantity": 26845,
        "quality": 2,
        "price": 8.6,
        "seller": {
            "id": 894140,
            "company": "AWA MARKETPLACE",
            "realmId": 0,
            "logo": "https://d1fxy698ilbz6u.cloudfront.net/logo/f737f48f080618c99e66d8b8c14a649fb7c1bcea.png",
            "certificates": 2,
            "contest_wins": 0,
            "npc": false,
            "courseId": null,
            "ip": "deb9a0"
        },
        "posted": "2023-03-11T10:28:01.971740+00:00",
        "fees": 6927
    },
    {
        "id": 54953547,
        "kind": 16,
        "quantity": 70,
        "quality": 0,
        "price": 8.6,
        "seller": {
            "id": 435454,
            "company": "Kings Pawn Industries",
            "realmId": 0,
            "logo": "",
            "certificates": 2,
            "contest_wins": 0,
            "npc": false,
            "courseId": null,
            "ip": "28a603"
        },
        "posted": "2023-03-17T10:58:54.716683+00:00",
        "fees": 19
    },
    {
        "id": 54953545,
        "kind": 16,
        "quantity": 70,
        "quality": 0,
        "price": 8.7,
        "seller": {
            "id": 435454,
            "company": "Kings Pawn Industries",
            "realmId": 0,
            "logo": "",
            "certificates": 2,
            "contest_wins": 0,
            "npc": false,
            "courseId": null,
            "ip": "28a603"
        },
        "posted": "2023-03-17T10:58:48.422255+00:00",
        "fees": 19
    },
    {
        "id": 54953542,
        "kind": 16,
        "quantity": 71,
        "quality": 0,
        "price": 8.8,
        "seller": {
            "id": 435454,
            "company": "Kings Pawn Industries",
            "realmId": 0,
            "logo": "",
            "certificates": 2,
            "contest_wins": 0,
            "npc": false,
            "courseId": null,
            "ip": "28a603"
        },
        "posted": "2023-03-17T10:58:43.554204+00:00",
        "fees": 19
    },
    {
        "id": 54953535,
        "kind": 16,
        "quantity": 72,
        "quality": 0,
        "price": 8.9,
        "seller": {
            "id": 435454,
            "company": "Kings Pawn Industries",
            "realmId": 0,
            "logo": "",
            "certificates": 2,
            "contest_wins": 0,
            "npc": false,
            "courseId": null,
            "ip": "28a603"
        },
        "posted": "2023-03-17T10:58:37.436036+00:00",
        "fees": 20
    },
    {
        "id": 54550994,
        "kind": 16,
        "quantity": 11017,
        "quality": 3,
        "price": 9.0,
        "seller": {
            "id": 894140,
            "company": "AWA MARKETPLACE",
            "realmId": 0,
            "logo": "https://d1fxy698ilbz6u.cloudfront.net/logo/f737f48f080618c99e66d8b8c14a649fb7c1bcea.png",
            "certificates": 2,
            "contest_wins": 0,
            "npc": false,
            "courseId": null,
            "ip": "deb9a0"
        },
        "posted": "2023-03-11T10:28:20.286580+00:00",
        "fees": 2975
    },
    {
        "id": 54953522,
        "kind": 16,
        "quantity": 72,
        "quality": 0,
        "price": 9.0,
        "seller": {
            "id": 435454,
            "company": "Kings Pawn Industries",
            "realmId": 0,
            "logo": "",
            "certificates": 2,
            "contest_wins": 0,
            "npc": false,
            "courseId": null,
            "ip": "28a603"
        },
        "posted": "2023-03-17T10:58:29.166102+00:00",
        "fees": 20
    },
    {
        "id": 54597051,
        "kind": 16,
        "quantity": 28999,
        "quality": 11,
        "price": 9.1,
        "seller": {
            "id": 98583,
            "company": "Mountaineers",
            "realmId": 0,
            "logo": "https://d1fxy698ilbz6u.cloudfront.net/logo/37890a08dea18a8dd936216c448ce9188ce1b3bf.png",
            "certificates": 10,
            "contest_wins": 0,
            "npc": false,
            "courseId": null,
            "ip": "a58f0a"
        },
        "posted": "2023-03-12T02:07:50.108087+00:00",
        "fees": 0
    },
    {
        "id": 54709452,
        "kind": 16,
        "quantity": 2000,
        "quality": 10,
        "price": 12.0,
        "seller": {
            "id": 1623152,
            "company": "Emerald 768",
            "realmId": 0,
            "logo": "https://d1fxy698ilbz6u.cloudfront.net/logo/6aa73e35c07d3dbebbd189dfb71537b913a27acb.png",
            "certificates": 1,
            "contest_wins": 0,
            "npc": false,
            "courseId": null,
            "ip": "b37b9b"
        },
        "posted": "2023-03-13T18:01:06.311301+00:00",
        "fees": 720
    }
]