[
    {
        "id": 54956754,
        "kind": 4,
        "quantity": 1010,
        "quality": 0,
        "price": 2.1,
        "seller": {
            "id": 2997500,
            "company": "DBS Company S. R. L",
            "realmId": 1,
            "logo": "",
            "certificates": 0,
            "contest_wins": 0,
            "npc": false,
            "courseId": null,
            "ip": "6fbd5e"
        },
        "posted": "2023-03-17T12:03:36.409730+00:00",
        "fees": 64
    },
    {
        "id": 54957058,
        "kind": 4,
        "quantity": 180,
        "quality": 0,
        "price": 2.1,
        "seller": {
            "id": 2741630,
            "company": "Ozons ltd.",
            "realmId": 1,
            "logo": "",
            "certificates": 0,
            "contest_wins": 0,
            "npc": false,
            "courseId": null,
            "ip": "940e9b"
        },
        "posted": "2023-03-17T12:09:46.774456+00:00",
        "fees": 12
    },
    {
        "id": 54923936,
        "kind": 4,
        "quantity": 11704,
        "quality": 0,
        "price": 2.15,
        "seller": {
            "id": 2663505,
            "company": "Normie",
            "realmId": 1,
            "logo": "",
            "certificates": 0,
            "contest_wins": 0,
            "npc": false,
            "courseId": null,
            "ip": "518ce2"
        },
        "posted": "2023-03-16T22:17:35.078353+00:00",
        "fees": 0
    },
    {
        "id": 54925185,
        "kind": 4,
        "quantity": 8500,
        "quality": 0,
        "price": 2.15,
        "seller": {
            "id": 2586158,
            "company": "Alpha Network Msia Inc",
            "realmId": 1,
            "logo": "",
            "certificates": 0,
            "contest_wins": 0,
            "npc": false,
            "courseId": null,
            "ip": "5b1393"
        },
        "posted": "2023-03-16T22:44:56.249019+00:00",
        "fees": 549
    },
    {
        "id": 54921442,
        "kind": 4,
        "quantity": 2000,
        "quality": 0,
        "price": 2.2,
        "seller": {
            "id": 2995180,
            "company": "Zed Co",
            "realmId": 1,
            "logo": "",
            "certificates": 0,
            "contest_wins": 0,
            "npc": false,
            "courseId": null,
            "ip": "3f2dcf"
        },
        "posted": "2023-03-16T21:30:32.337825+00:00",
        "fees": 132
    },
    {
        "id": 54753777,
        "kind": 4,
        "quantity": 8232,
        "quality": 0,
        "price": 2.25,
        "seller": {
            "id": 2870797,
            "company": "Starry Corp",
            "realmId": 1,
            "logo": "https://d1fxy698ilbz6u.cloudfront.net/logo/b2dbbf76d3068f511e2fb84bc4f39c95d3d42fe7.png",
            "certificates": 0,
            "contest_wins": 0,
            "npc": false,
            "courseId": null,
            "ip": "6a0963"
        },
        "posted": "2023-03-14T12:35:14.129475+00:00",
        "fees": 557
    },
    {
        "id": 54939654,
        "kind": 4,
        "quantity": 25241,
        "quality": 2,
        "price": 2.3,
        "seller": {
            "id": 2582045,
            "company": "Duster",
            "realmId": 1,
            "logo": "https://d1fxy698ilbz6u.cloudfront.net/logo/42ce11e7620e2bd21844ff3843a23a234ddac7fe.png",
            "certificates": 0,
            "contest_wins": 0,
            "npc": false,
            "courseId": null,
            "ip": "2a90fe"
        },
        "posted": "2023-03-17T05:39:27.104063+00:00",
        "fees": 1742
    },
    {
        "id": 54651027,
        "kind": 4,
        "quantity": 223,
        "quality": 0,
        "price": 2.3,
        "seller": {
            "id": 2993800,
            "company": "Madinlolo",
            "realmId": 1,
            "logo": "",
            "certificates": 0,
            "contest_wins": 0,
            "npc": false,
            "courseId": null,
            "ip": "339f96"
        },
        "posted": "2023-03-12T20:47:18.609441+00:00",
        "fees": 16
    },
    {
        "id": 54752659,
        "kind": 4,
        "quantity": 1859,
        "quality": 0,
        "price": 2.3,
        "seller": {
            "id": 2604107,
            "company": "Etruritaly",
            "realmId": 1,
            "logo": "https://d1fxy698ilbz6u.cloudfront.net/logo/9e138abca85b0b3706f173133c202d96afedf9cf.png",
            "certificates": 0,
            "contest_wins": 0,
            "npc": false,
            "courseId": null,
            "ip": "19c7bf"
        },
        "posted": "2023-03-14T09:45:17.445061+00:00",
        "fees": 129
    },
    {
        "id": 54520435,
        "kind": 4,
        "quantity": 21100,
        "quality": 1,
        "price": 2.35,
        "seller": {
            "id": 2608062,
            "company": "GG seeds and ethanol",
            "realmId": 1,
            "logo": "",
            "certificates": 0,
            "contest_wins": 0,
            "npc": false,
            "courseId": null,
            "ip": "f33d33"
        },
        "posted": "2023-03-10T21:58:08.858391+00:00",
        "fees": 0
    },
    {
        "id": 54905064,
        "kind": 4,
        "quantity": 1500,
        "quality": 1,
        "price": 2.35,
        "seller": {
            "id": 2582901,
            "company": "Green Leaf Holdings",
            "realmId": 1,
            "logo": "https://d1fxy698ilbz6u.cloudfront.net/logo/54b4c4a19d6f084cef7e09466bdbd753c591042f.png",
            "certificates": 0,
            "contest_wins": 0,
            "npc": false,
            "courseId": null,
            "ip": "e0c4b9"
        },
        "posted": "2023-03-16T16:34:05.213705+00:00",
        "fees": 106
    },
    {
        "id": 54905077,
        "kind": 4,
        "quantity": 2000,
        "quality": 1,
        "price": 2.4,
        "seller": {
            "id": 2582901,
            "company": "Green Leaf Holdings",
            "realmId": 1,
            "logo": "https://d1fxy698ilbz6u.cloudfront.net/logo/54b4c4a19d6f084cef7e09466bdbd753c591042f.png",
            "certificates": 0,
            "contest_wins": 0,
            "npc": false,
            "courseId": null,
            "ip": "e0c4b9"
        },
        "posted": "2023-03-16T16:34:18.716862+00:00",
        "fees": 144
    },
    {
        "id": 54924921,
        "kind": 4,
        "quantity": 190,
        "quality": 0,
        "price": 2.4,
        "seller": {
            "id": 2996216,
            "company": "Zylberkan Ltda",
            "realmId": 1,
            "logo": "https://d1fxy698ilbz6u.cloudfront.net/logo/cca6f9fc385c39053c0fb8f44719f5a0a814f7bf.png",
            "certificates": 0,
            "contest_wins": 0,
            "npc": false,
            "courseId": null,
            "ip": "6a54df"
        },
        "posted": "2023-03-16T22:38:55.736295+00:00",
        "fees": 14
    },
    {
        "id": 54906822,
        "kind": 4,
        "quantity": 8557,
        "quality": 2,
        "price": 2.45,
        "seller": {
            "id": 2583692,
            "company": "Lost Horizon",
            "realmId": 1,
            "logo": "",
            "certificates": 0,
            "contest_wins": 0,
            "npc": false,
            "courseId": null,
            "ip": "deb045"
        },
        "posted": "2023-03-16T17:08:24.540676+00:00",
        "fees": 629
    },
    {
        "id": 54848836,
        "kind": 4,
        "quantity": 30,
        "quality": 0,
        "price": 2.5,
        "seller": {
            "id": 3000734,
            "company": "Pajinek",
            "realmId": 1,
            "logo": "",
            "certificates": 0,
            "contest_wins": 0,
            "npc": false,
            "courseId": null,
            "ip": "3370d9"
        },
        "posted": "2023-03-15T19:42:45.209821+00:00",
        "fees": 3
    },
    {
        "id": 54768868,
        "kind": 4,
        "quantity": 2500,
        "quality": 3,
        "price": 2.75,
        "seller": {
            "id": 2595814,
            "company": "Nitopakito",
            "realmId": 1,
            "logo": "",
            "certificates": 4,
            "contest_wins": 0,
            "npc": false,
            "courseId": null,
            "ip": "6f612b"
        },
        "posted": "2023-03-14T15:19:08.975232+00:00",
        "fees": 207
    },
    {
        "id": 54517814,
        "kind": 4,
        "quantity": 1000,
        "quality": 3,
        "price": 4.0,
        "seller": {
            "id": 2585836,
            "company": "Kronk ko.",
            "realmId": 1,
            "logo": "https://d1fxy698ilbz6u.cloudfront.net/logo/5d5f2e4ac67a71a5d7cb4935ada20d60b47ad7df.png",
            "certificates": 0,
            "contest_wins": 0,
            "npc": false,
            "courseId": null,
            "ip": "cdc0a7"
        },
        "posted": "2023-03-10T21:09:47.885651+00:00",
        "fees": 120
    }
]